listFile/__init__.py
listFile/__main__.py
listFile/list_file.py
listAllTheFile-0.0.1.dist-info/LICENSE
listAllTheFile-0.0.1.dist-info/METADATA
listAllTheFile-0.0.1.dist-info/WHEEL
listAllTheFile-0.0.1.dist-info/entry_points.txt
listAllTheFile-0.0.1.dist-info/top_level.txt
listAllTheFile-0.0.1.dist-info/RECORD
