Metadata-Version: 2.1
Name: listAllTheFile
Version: 0.0.1
Summary: A package for listing file names in directory
Home-page: https://github.com/zhangshyue/listFile
Author: Shiyue Zhang
Author-email: zhangshiyuez@gmail.com
License: MIT
Platform: UNKNOWN
License-File: LICENSE
